{
  "name": "Anne Briggs",
  "age": 31,
  "address": {
    "street": "Riwa Pike",
    "city": "Rodfenov",
    "state": "AR",
    "zip": "05047"
  },
  "contact": {
    "phone": "(359) 671-5762",
    "servicePhone": "800192885"
  },
  "birthday": "1974-07-13T08:42:38.398Z",
  "ip": "202.49.15.63",
  "foo": "bar",
  "profile": {
    "about": "Wom vaton ti tenilum fidnu vead powophu tabhig selaw dum ro iwanov kac joersum zieveved mokpovta. Cevsuped lirmiido gos til ewa hutzajuwi wurbe obe eheap rebmugfoh elo haca sewafnik. Hifetoej cieb loudoawa jopripki woh wewfu lika em rihho roki gafo avkos vo tecdus gi. Nu nofoj hedev mol po kafbafzi jiz fac neera sepeksi hi te duketo.",
    "bio": "Gatcithe fuphab incadu cu ri ja ke mawawpir cuwringa fibeh azelecu nefkeltu watvutzam nomduhlap jurbi se. Cauvi pev mitucmek soino isebih ocosivduc va deeso mijnop ejcurviz wot jenhuhi jevufal vowge. Saw bapu ekakib wapurwo cidip biw kofef pehes viphos suha mazelze fi de ol. Mom apusiviw es koggoro zejum zo mahajen vop if poze evcep cuconuper ciw guhveohu vum agkeid umemec gu. Gufehiw jipepro wa ipo rim nipowa wa pocsusu poja pewsecak obteg paplutog."
  },
  "apiKey": "3e927552be3e8679b9dd5167e1ccbad39fbfeb96b6c77be76b5fefc2b9a6c2fc",
  "currency": {
    "code": "ILS",
    "name": "Israel Shekel"
  }
}