{
  "name": "Corey Patterson",
  "age": 24,
  "address": {
    "street": "Ziva Circle",
    "city": "Seczafra",
    "state": "MA",
    "zip": "11038"
  },
  "contact": {
    "phone": "(702) 999-3846",
    "servicePhone": "800718946"
  },
  "birthday": "1987-12-31T08:32:27.390Z",
  "ip": "240.121.65.250",
  "foo": "bar",
  "profile": {
    "about": "Dejit fus bomvauma jo hawfoge geswukiv nod rumnuddud wajler ako lure hepla zukvoskas. Vulcaktok fokarne ecunaplup remse ufehurob afisop fitafbod kebi zobvev bo mitohad kaebul fij ewigaho ginu. Ditcerjuf dizwa rezisib jofu humfit madupe opebas nehe gocinno binukku rehtew cotocgi. Pocaf ohopobca poozivo zivwema hu sarzegrov lesor joej reasmaj wavumoir fohevuugi hic we pi pagepuh hin mek enutiwnu.",
    "bio": "Moarigus sej iru ic iva tav lodis iswibnuk lerbul hig vaviw zadoj ok fusocac hi hetopov. Kuv buttore ito teribe beorolig zodgi bor kov digah nu hej mehec wudpuwe. Vik hococpe gaklum oh orbusmij vuv tubilwiz gov zomehosu ces bot en poc bikuh jovta kebof."
  },
  "apiKey": "7f7ce31d498288cf8b6b8cf15e65d071ac27595fbcb2391dfd2552d0c3d17ef3",
  "currency": {
    "code": "SPL",
    "name": "Seborga Luigino"
  }
}