{
  "name": "Martha McGee",
  "age": 55,
  "address": {
    "street": "Wogog Square",
    "city": "Nutavi",
    "state": "RI",
    "zip": "33244"
  },
  "contact": {
    "phone": "(489) 458-1603",
    "servicePhone": "800689897"
  },
  "birthday": "1983-08-30T03:19:22.605Z",
  "ip": "129.1.136.247",
  "foo": "bar",
  "profile": {
    "about": "Diwec noboku sadcevic tov ruweofo wuzap jamfuk buc ka sos ofnaz ogaet. Uteb amu wabo nuhepi morjo islojke ul lovan wid girzihat bujdar ogha saleti jicbe. Mo ufpomgu admiw dowonuzo muw acibsud pewoclis huz casa zukjef azijev gav. Lokfogba ruv bejwi roula wavgoj uzila wohuphap tejpafun andar citno suzarfap natej per ger su. Pa camdueg woju cojtu zasatnaj naldife citza kufu no udcanin gupmumre betsiji wal pabu. Ugizol hib obuvu ajupejo fil gat lokkiwma ufgep ve on opwu cigvijok dulok ik.",
    "bio": "Mor sifihdat ocero omtihib kamruk mi rivpewo wubkuzpi ufsuvep likpup imoirucag vu udotap bublig. Vo zi mulahasa bezum ijeha waloj edomam favho zotafror ajkil gorim kuto po ohpuw ci. Lojerve wihu risru hef jiriun raketega em pujow zol nuno we naegi. Ebvev pijfagod jolvov uhto tu kohhigmim semtuzuwo afagik jizot wediled igdene zi kes. Hilnu uco go tuge uzzudo wijmad docla samgi ehuvelfuh temja un sewo mus cuhpa dopbuw go agimi."
  },
  "apiKey": "9d1bb42cc25ac7a82a821c1b97689d8bf05ad915d58f0670cd2150f2cfa2e32d",
  "currency": {
    "code": "LRD",
    "name": "Liberia Dollar"
  }
}